puregen/__init__.py
puregen/__main__.py
puregen-0.1.0.dist-info/METADATA
puregen-0.1.0.dist-info/WHEEL
puregen-0.1.0.dist-info/entry_points.txt
puregen-0.1.0.dist-info/top_level.txt
puregen-0.1.0.dist-info/RECORD
